{
  "bookings": [
    {
      "id": "BK10001",
      "orderCode": 100010001,
      "roomId": "vip-vuong",
      "roomName": "VIP Vuông (T1)",
      "checkIn": "2026-08-14",
      "checkOut": "2026-08-16",
      "nights": 2,
      "guestName": "Nguyễn Văn An",
      "guestPhone": "0901234567",
      "guestEmail": "an.nguyen@email.com",
      "guestNote": "Đến muộn sau 22h",
      "totalAmount": 1800000,
      "status": "CONFIRMED",
      "paymentRef": "DATPHONG 100010001 0901234567",
      "confirmedAt": "2026-07-22T10:30:00.000Z",
      "expiredAt": "2026-07-22T11:00:00.000Z",
      "createdAt": "2026-07-22T10:25:00.000Z"
    },
    {
      "id": "BK10002",
      "orderCode": 100020002,
      "roomId": "a02",
      "roomName": "Phòng A02 (Khu A)",
      "checkIn": "2026-08-15",
      "checkOut": "2026-08-17",
      "nights": 2,
      "guestName": "Trần Thị Bình",
      "guestPhone": "0912345678",
      "guestEmail": "binh.tran@gmail.com",
      "guestNote": "Có 2 trẻ em 5 và 8 tuổi",
      "totalAmount": 2100000,
      "status": "CONFIRMED",
      "paymentRef": "DATPHONG 100020002 0912345678",
      "confirmedAt": "2026-07-22T09:15:00.000Z",
      "expiredAt": "2026-07-22T09:45:00.000Z",
      "createdAt": "2026-07-22T09:10:00.000Z"
    },
    {
      "id": "BK10003",
      "orderCode": 100030003,
      "roomId": "b01",
      "roomName": "Phòng B01 (Khu B)",
      "checkIn": "2026-08-16",
      "checkOut": "2026-08-18",
      "nights": 2,
      "guestName": "Lê Minh Cường",
      "guestPhone": "0923456789",
      "guestEmail": "cuong.le@outlook.com",
      "totalAmount": 1600000,
      "status": "PENDING_CONFIRM",
      "paymentRef": "DATPHONG 100030003 0923456789",
      "expiredAt": "2026-07-23T14:30:00.000Z",
      "createdAt": "2026-07-23T14:25:00.000Z"
    }
  ]
}